youpi/__init__.py
youpi/cache.py
youpi/semi_singleton.py
youpi/stream.py
youpi/streamlist.py
youpi/youtube.py
youpi-0.1.5.dist-info/LICENSE
youpi-0.1.5.dist-info/METADATA
youpi-0.1.5.dist-info/WHEEL
youpi-0.1.5.dist-info/top_level.txt
youpi-0.1.5.dist-info/RECORD
